ourskyai_sda_api/__init__.py
ourskyai_sda_api/api_client.py
ourskyai_sda_api/api_response.py
ourskyai_sda_api/configuration.py
ourskyai_sda_api/exceptions.py
ourskyai_sda_api/py.typed
ourskyai_sda_api/rest.py
ourskyai_sda_api/api/__init__.py
ourskyai_sda_api/api/default_api.py
ourskyai_sda_api/models/__init__.py
ourskyai_sda_api/models/astrometric_offsets.py
ourskyai_sda_api/models/empty_success.py
ourskyai_sda_api/models/filter_type.py
ourskyai_sda_api/models/fits_header.py
ourskyai_sda_api/models/image_set_type.py
ourskyai_sda_api/models/location.py
ourskyai_sda_api/models/mount_type.py
ourskyai_sda_api/models/observation_bounding_box.py
ourskyai_sda_api/models/observation_quality.py
ourskyai_sda_api/models/observation_result.py
ourskyai_sda_api/models/observation_state.py
ourskyai_sda_api/models/orbit_type.py
ourskyai_sda_api/models/satellite_target_tracking_status.py
ourskyai_sda_api/models/search_completed_reason.py
ourskyai_sda_api/models/shutter_type.py
ourskyai_sda_api/models/successful_create.py
ourskyai_sda_api/models/successful_delete.py
ourskyai_sda_api/models/tracking_type.py
ourskyai_sda_api/models/v1_blackout_volume_request.py
ourskyai_sda_api/models/v1_create_direct_task_instruction_request.py
ourskyai_sda_api/models/v1_create_image_set_image_request.py
ourskyai_sda_api/models/v1_create_image_set_image_response.py
ourskyai_sda_api/models/v1_create_image_set_request.py
ourskyai_sda_api/models/v1_create_organization_target_request.py
ourskyai_sda_api/models/v1_create_satellite_target_request.py
ourskyai_sda_api/models/v1_create_search_instruction_request.py
ourskyai_sda_api/models/v1_create_survey_instruction_request.py
ourskyai_sda_api/models/v1_create_webhook_configuration_request.py
ourskyai_sda_api/models/v1_create_webhook_test_request.py
ourskyai_sda_api/models/v1_get_satellite_targets_response.py
ourskyai_sda_api/models/v1_ground_station_participant.py
ourskyai_sda_api/models/v1_hfr_star.py
ourskyai_sda_api/models/v1_image_file_type.py
ourskyai_sda_api-1.3.9356.dist-info/METADATA
ourskyai_sda_api-1.3.9356.dist-info/WHEEL
ourskyai_sda_api-1.3.9356.dist-info/top_level.txt
ourskyai_sda_api-1.3.9356.dist-info/RECORD
